codeuchain/__init__.py
codeuchain/py.typed
codeuchain/core/__init__.py
codeuchain/core/chain.py
codeuchain/core/context.py
codeuchain/core/link.py
codeuchain/core/middleware.py
codeuchain/utils/__init__.py
codeuchain/utils/error_handling.py
codeuchain-1.1.0.dist-info/licenses/LICENSE
codeuchain-1.1.0.dist-info/METADATA
codeuchain-1.1.0.dist-info/WHEEL
codeuchain-1.1.0.dist-info/top_level.txt
codeuchain-1.1.0.dist-info/RECORD
